{
  "type": "FeatureCollection", 
  "features": [
    {
      "geometry": {
        "type": "Polygon", 
        "coordinates": [
          [
            [
              6.910, 
              45.495
            ], 
            [
              6.910, 
              45.505
            ], 
            [
              6.923, 
              45.505
            ], 
            [
              6.923, 
              45.495
            ], 
            [
              6.910, 
              45.495
            ]
          ]
        ]
      }, 
      "type": "Feature", 
      "properties": {
        "lang": "ENG", 
        "alias_ENG_V": [
          "TGF"
        ], 
        "name": "Tignes Airport", 
        "hierarchy": [
          "woe:localadmin=12661721", 
          "woe:county=12597180", 
          "woe:state=7153329", 
          "woe:country=23424819", 
          "woe:planet=1"
        ], 
        "woeid": 12523832, 
        "provider": "geoplanet 7.6.0", 
        "ne_longitude": 6.923, 
        "longitude": 6.917, 
        "parent_woeid": 12661721, 
        "placetype": "airport", 
        "latitude": 45.500, 
        "iso": "FR", 
        "sw_latitude": 45.495, 
        "ne_latitude": 45.505, 
        "alias_FRE_V": [
          "TGF A\u00e9roport"
        ], 
        "sw_longitude": 6.910, 
        "fullname": "Tignes Airport, Les Boisses, Rhone-Alpes, France", 
        "alias_FRE_S": [
          "Aeroport TGF"
        ], 
        "date_indexed": "2010-12-02T12:04:01Z"
      }, 
      "id": 12523832
    }
  ]
}