{
  "type": "FeatureCollection", 
  "features": [
    {
      "geometry": {
        "type": "Polygon", 
        "coordinates": [
          [
            [
              -83.922, 
              43.983
            ], 
            [
              -83.922, 
              43.990
            ], 
            [
              -83.912, 
              43.990
            ], 
            [
              -83.912, 
              43.983
            ], 
            [
              -83.922, 
              43.983
            ]
          ]
        ]
      }, 
      "type": "Feature", 
      "properties": {
        "lang": "ENG", 
        "woeid": 29388250, 
        "name": "Dudley Airport", 
        "ne_latitude": 43.990, 
        "provider": "geoplanet 7.6.0", 
        "ne_longitude": -83.912, 
        "longitude": -83.919, 
        "placetype": "Airport", 
        "iso": "US", 
        "date_indexed": "2010-12-02T18:39:52Z", 
        "parent_woeid": 2472388, 
        "latitude": 43.983, 
        "sw_longitude": -83.922, 
        "fullname": "Dudley Airport, Pine River, Michigan, Arenac, United States", 
        "sw_latitude": 43.983
      }, 
      "id": 29388250
    }
  ]
}