{
  "type": "FeatureCollection", 
  "features": [
    {
      "geometry": {
        "type": "Polygon", 
        "coordinates": [
          [
            [
              -95.589348, 
              30.737280
            ], 
            [
              -95.589348, 
              30.754919
            ], 
            [
              -95.584831, 
              30.754919
            ], 
            [
              -95.584831, 
              30.737280
            ], 
            [
              -95.589348, 
              30.737280
            ]
          ]
        ]
      }, 
      "type": "Feature", 
      "properties": {
        "lang": "ENG", 
        "alias_ENG_V": [
          "UTS"
        ], 
        "name": "Huntsville Municipal Airport", 
        "hierarchy": [
          "woe:county=12590242", 
          "woe:state=2347602", 
          "woe:country=23424977", 
          "woe:planet=1"
        ], 
        "ne_latitude": 30.754919, 
        "sw_latitude": 30.737280, 
        "ne_longitude": -95.584831, 
        "longitude": -95.588478, 
        "iso": "US", 
        "woe:placetype": "airport", 
        "provider": "geoplanet 7.6.0", 
        "latitude": 30.737749, 
        "sw_longitude": -95.589348, 
        "fullname": "Huntsville Municipal Airport, Huntsville, Texas, United States", 
        "woe:id": 12520263, 
        "date_indexed": "2010-12-02T18:39:38Z", 
        "iata:code": "UTS"
      }, 
      "id": 12520263
    }
  ]
}