{
  "type": "FeatureCollection", 
  "features": [
    {
      "geometry": {
        "type": "Polygon", 
        "coordinates": [
          [
            [
              -86.385, 
              33.968
            ], 
            [
              -86.385, 
              33.977
            ], 
            [
              -86.374, 
              33.977
            ], 
            [
              -86.374, 
              33.968
            ], 
            [
              -86.385, 
              33.968
            ]
          ]
        ]
      }, 
      "type": "Feature", 
      "properties": {
        "lang": "ENG", 
        "woeid": 12521607, 
        "name": "Robbins Field Airport", 
        "ne_latitude": 33.977, 
        "provider": "geoplanet 7.6.0", 
        "ne_longitude": -86.374, 
        "longitude": -86.379, 
        "placetype": "Airport", 
        "iso": "US", 
        "date_indexed": "2010-12-02T18:39:24Z", 
        "parent_woeid": 2503629, 
        "latitude": 33.972, 
        "sw_longitude": -86.385, 
        "fullname": "Robbins Field Airport, Taits Gap, Alabama, Blount, United States", 
        "sw_latitude": 33.968
      }, 
      "id": 12521607
    }
  ]
}