{
  "type": "FeatureCollection", 
  "features": [
    {
      "geometry": {
        "type": "Polygon", 
        "coordinates": [
          [
            [
              -23.181, 
              15.216
            ], 
            [
              -23.181, 
              15.225
            ], 
            [
              -23.171, 
              15.225
            ], 
            [
              -23.171, 
              15.216
            ], 
            [
              -23.181, 
              15.216
            ]
          ]
        ]
      }, 
      "type": "Feature", 
      "properties": {
        "lang": "ENG", 
        "alias_ENG_V": [
          "MMO"
        ], 
        "name": "Maio Airport", 
        "hierarchy": [
          "woe:state=2345124", 
          "woe:country=23424794", 
          "woe:planet=1"
        ], 
        "provider": "geoplanet 7.6.0", 
        "ne_longitude": -23.171, 
        "longitude": -23.176, 
        "latitude": 15.221, 
        "iso": "CV", 
        "date_indexed": "2010-12-02T12:16:16Z", 
        "ne_latitude": 15.225, 
        "sw_longitude": -23.181, 
        "fullname": "Maio Airport, Vila do Maio, Maio, Cape Verde", 
        "woe:id": 12512492, 
        "sw_latitude": 15.216, 
        "woe:placetype": "airport"
      }, 
      "id": 12512492
    }
  ]
}