{
  "type": "FeatureCollection", 
  "features": [
    {
      "geometry": {
        "type": "Polygon", 
        "coordinates": [
          [
            [
              88.732933, 
              57.124149
            ], 
            [
              88.732933, 
              57.133251
            ], 
            [
              88.749672, 
              57.133251
            ], 
            [
              88.749672, 
              57.124149
            ], 
            [
              88.732933, 
              57.124149
            ]
          ]
        ]
      }, 
      "type": "Feature", 
      "properties": {
        "lang": "ENG", 
        "name": "Rubino Airport", 
        "hierarchy": [
          "woe:county=12597890", 
          "woe:state=20070524", 
          "woe:country=23424936", 
          "woe:planet=1"
        ], 
        "ne_latitude": 57.133251, 
        "ne_longitude": 88.749672, 
        "longitude": 88.741302, 
        "iso": "RU", 
        "sw_latitude": 57.124149, 
        "provider": "geoplanet 7.6.0", 
        "latitude": 57.128700, 
        "sw_longitude": 88.732933, 
        "fullname": "Rubino Airport, Krasnoyarskiy Kray, Tyukhtetsky, Russia", 
        "woe:id": 12516791, 
        "date_indexed": "2010-12-02T16:11:04Z", 
        "woe:placetype": "airport"
      }, 
      "id": 12516791
    }
  ]
}