{
  "type": "FeatureCollection", 
  "features": [
    {
      "geometry": {
        "type": "MultiPolygon", 
        "coordinates": [
          [
            [
              [
                -74.363, 
                45.640
              ], 
              [
                -74.363, 
                45.639
              ], 
              [
                -74.363, 
                45.639
              ], 
              [
                -74.367, 
                45.640
              ], 
              [
                -74.363, 
                45.641
              ], 
              [
                -74.363, 
                45.640
              ]
            ]
          ]
        ]
      }, 
      "type": "Feature", 
      "properties": {
        "lang": "ENG", 
        "ne_latitude": 45.641, 
        "name": "Lachute Airport", 
        "hierarchy": [
          "woe:county=29375247", 
          "woe:state=2344924", 
          "woe:country=23424775", 
          "woe:planet=1"
        ], 
        "provider": "geoplanet 7.6.0", 
        "ne_longitude": -74.363, 
        "longitude": -74.364, 
        "iso": "CA", 
        "date_indexed": "2010-12-02T10:23:54Z", 
        "latitude": 45.640, 
        "sw_longitude": -74.367, 
        "fullname": "Lachute Airport, Lachute, Quebec, Canada", 
        "woe:id": 12511727, 
        "sw_latitude": 45.639, 
        "woe:placetype": "airport"
      }, 
      "id": 12511727
    }
  ]
}