{
  "type": "FeatureCollection", 
  "features": [
    {
      "geometry": {
        "type": "Polygon", 
        "coordinates": [
          [
            [
              12.169100, 
              51.824268
            ], 
            [
              12.169100, 
              51.834728
            ], 
            [
              12.197710, 
              51.834728
            ], 
            [
              12.197710, 
              51.824268
            ], 
            [
              12.169100, 
              51.824268
            ]
          ]
        ]
      }, 
      "type": "Feature", 
      "properties": {
        "lang": "GER", 
        "name": "Flugplatz Dessau", 
        "hierarchy": [
          "woe:localadmin=12625862", 
          "woe:county=12596999", 
          "woe:state=2345494", 
          "woe:country=23424829", 
          "woe:planet=1"
        ], 
        "ne_latitude": 51.834728, 
        "ne_longitude": 12.197710, 
        "longitude": 12.182890, 
        "iso": "DE", 
        "sw_latitude": 51.824268, 
        "provider": "geoplanet 7.6.0", 
        "latitude": 51.834492, 
        "sw_longitude": 12.169100, 
        "fullname": "Flugplatz Dessau, Dessau, Saxony-Anhalt, Germany", 
        "woe:id": 56052135, 
        "date_indexed": "2010-12-02T09:50:31Z", 
        "woe:placetype": "airport"
      }, 
      "id": 56052135
    }
  ]
}