{
  "type": "FeatureCollection", 
  "features": [
    {
      "geometry": {
        "type": "Polygon", 
        "coordinates": [
          [
            [
              -96.776, 
              39.042
            ], 
            [
              -96.776, 
              39.062
            ], 
            [
              -96.752, 
              39.062
            ], 
            [
              -96.752, 
              39.042
            ], 
            [
              -96.776, 
              39.042
            ]
          ]
        ]
      }, 
      "type": "Feature", 
      "properties": {
        "lang": "ENG", 
        "alias_ENG_V": [
          "FRI Airport"
        ], 
        "woe:placetype": "airport", 
        "name": "Marshall Army Air Field", 
        "woe:parent": 12588401, 
        "hierarchy": [
          "woe:county=12588401", 
          "woe:state=2347575", 
          "woe:country=23424977", 
          "woe:planet=1"
        ], 
        "ne_latitude": 39.062, 
        "ne_longitude": -96.752, 
        "longitude": -96.760, 
        "children": [
          "woe:building=2166181019", 
          "woe:building=2166181018", 
          "woe:building=2166181015", 
          "woe:building=2166180992", 
          "woe:building=2166180993", 
          "woe:building=2166180991", 
          "woe:building=2166180998", 
          "woe:building=2166180994", 
          "woe:building=2166180990", 
          "woe:building=2166181032", 
          "woe:building=2166180989", 
          "woe:building=2166181006", 
          "woe:building=2166181002", 
          "woe:building=2166181003", 
          "woe:building=2166181000", 
          "woe:building=2166181027", 
          "woe:building=2166181023", 
          "woe:building=2166181028", 
          "woe:building=2166181024"
        ], 
        "sw_longitude": -96.776, 
        "geonames:id": 4275108, 
        "provider": "geoplanet 7.6.0", 
        "latitude": 39.062, 
        "iso": "US", 
        "fullname": "Marshall Army Air Field, Grandview Plaza, Kansas, United States", 
        "osm:node": 368388786, 
        "date_indexed": "2010-12-02T18:39:38Z", 
        "woe:id": 12520815, 
        "sw_latitude": 39.042, 
        "iata:code": "FRI"
      }, 
      "id": 12520815
    }
  ]
}