{
  "type": "FeatureCollection", 
  "features": [
    {
      "geometry": {
        "type": "Polygon", 
        "coordinates": [
          [
            [
              -55.922, 
              -27.305
            ], 
            [
              -55.922, 
              -27.295
            ], 
            [
              -55.912, 
              -27.295
            ], 
            [
              -55.912, 
              -27.305
            ], 
            [
              -55.922, 
              -27.305
            ]
          ]
        ]
      }, 
      "type": "Feature", 
      "properties": {
        "lang": "ENG", 
        "alias_ENG_V": [
          "ENO Airport"
        ], 
        "name": "Teniente Prim Alarcon Airport", 
        "placetype": "airport", 
        "hierarchy": [
          "woe:county=26810861", 
          "woe:state=2346457", 
          "woe:country=23424917", 
          "woe:planet=1"
        ], 
        "woeid": 12523567, 
        "ne_longitude": -55.912, 
        "longitude": -55.917, 
        "parent_woeid": 26810861, 
        "ne_latitude": -27.295, 
        "iso": "PY", 
        "sw_latitude": -27.305, 
        "provider": "geoplanet 7.6.0", 
        "latitude": -27.300, 
        "sw_longitude": -55.922, 
        "fullname": "Teniente Prim Alarcon Airport, San Juan del Paran\u00e1, Itap\u00faa, Paraguay", 
        "date_indexed": "2010-12-02T12:08:38Z"
      }, 
      "id": 12523567
    }
  ]
}