{
  "type": "FeatureCollection", 
  "features": [
    {
      "geometry": {
        "type": "Polygon", 
        "coordinates": [
          [
            [
              -76.195, 
              53.587
            ], 
            [
              -76.195, 
              53.596
            ], 
            [
              -76.180, 
              53.596
            ], 
            [
              -76.180, 
              53.587
            ], 
            [
              -76.195, 
              53.587
            ]
          ]
        ]
      }, 
      "type": "Feature", 
      "properties": {
        "lang": "ENG", 
        "alias_ENG_V": [
          "YAD Airport"
        ], 
        "name": "Moose Lake Airport", 
        "placetype": "airport", 
        "hierarchy": [
          "woe:county=29375239", 
          "woe:state=2344924", 
          "woe:country=23424775", 
          "woe:planet=1"
        ], 
        "woeid": 12524073, 
        "ne_longitude": -76.180, 
        "longitude": -76.188, 
        "parent_woeid": 29375239, 
        "ne_latitude": 53.596, 
        "iso": "CA", 
        "sw_latitude": 53.587, 
        "provider": "geoplanet 7.6.0", 
        "latitude": 53.592, 
        "sw_longitude": -76.195, 
        "fullname": "Moose Lake Airport, Radisson, Quebec, Canada", 
        "iata_code": "YAD", 
        "date_indexed": "2010-12-02T10:23:54Z"
      }, 
      "id": 12524073
    }
  ]
}