{
  "type": "FeatureCollection", 
  "features": [
    {
      "geometry": {
        "type": "Polygon", 
        "coordinates": [
          [
            [
              -97.040, 
              50.045
            ], 
            [
              -97.040, 
              50.055
            ], 
            [
              -97.026, 
              50.055
            ], 
            [
              -97.026, 
              50.045
            ], 
            [
              -97.040, 
              50.045
            ]
          ]
        ]
      }, 
      "type": "Feature", 
      "properties": {
        "lang": "ENG", 
        "placetype": "airport", 
        "name": "Winnipeg St Andrews Airport", 
        "hierarchy": [
          "woe:county=29375231", 
          "woe:state=2344917", 
          "woe:country=23424775", 
          "woe:planet=1"
        ], 
        "woeid": 12511917, 
        "ne_longitude": -97.026, 
        "longitude": -97.033, 
        "parent_woeid": 29375231, 
        "ne_latitude": 50.055, 
        "iso": "CA", 
        "sw_latitude": 50.045, 
        "provider": "geoplanet 7.6.0", 
        "latitude": 50.050, 
        "sw_longitude": -97.040, 
        "fullname": "Winnipeg St Andrews Airport, St. Andrews, Manitoba, Canada", 
        "date_indexed": "2010-12-02T10:23:54Z"
      }, 
      "id": 12511917
    }
  ]
}