{
  "type": "FeatureCollection", 
  "features": [
    {
      "geometry": {
        "type": "Polygon", 
        "coordinates": [
          [
            [
              45.186699, 
              24.720449
            ], 
            [
              45.186699, 
              24.729549
            ], 
            [
              45.196701, 
              24.729549
            ], 
            [
              45.196701, 
              24.720449
            ], 
            [
              45.186699, 
              24.720449
            ]
          ]
        ]
      }, 
      "type": "Feature", 
      "properties": {
        "lang": "ENG", 
        "name": "Kp 718 Airport", 
        "hierarchy": [
          "woe:county=56120188", 
          "woe:state=2346951", 
          "woe:country=23424938", 
          "woe:planet=1"
        ], 
        "ne_latitude": 24.729549, 
        "ne_longitude": 45.196701, 
        "longitude": 45.191700, 
        "iso": "SA", 
        "sw_latitude": 24.720449, 
        "provider": "geoplanet 7.6.0", 
        "latitude": 24.725000, 
        "sw_longitude": 45.186699, 
        "fullname": "Kp 718 Airport, Labkhah, Ar Riyad, Saudi Arabia", 
        "woe:id": 12517351, 
        "date_indexed": "2010-12-02T09:34:42Z", 
        "woe:placetype": "airport"
      }, 
      "id": 12517351
    }
  ]
}