{
  "type": "FeatureCollection", 
  "features": [
    {
      "geometry": {
        "type": "Polygon", 
        "coordinates": [
          [
            [
              16.952, 
              -12.409
            ], 
            [
              16.952, 
              -12.400
            ], 
            [
              16.961, 
              -12.400
            ], 
            [
              16.961, 
              -12.409
            ], 
            [
              16.952, 
              -12.409
            ]
          ]
        ]
      }, 
      "type": "Feature", 
      "properties": {
        "lang": "ENG", 
        "woeid": 12510436, 
        "name": "Kuito Airport", 
        "alias_ENG_V": [
          "SVP"
        ], 
        "ne_latitude": -12.400, 
        "provider": "geoplanet 7.6.0", 
        "ne_longitude": 16.961, 
        "longitude": 16.957, 
        "placetype": "Airport", 
        "iso": "AO", 
        "date_indexed": "2010-12-02T17:52:20Z", 
        "parent_woeid": 1261704, 
        "latitude": -12.404, 
        "sw_longitude": 16.952, 
        "fullname": "Kuito Airport, Kuito, Bie, Angola", 
        "sw_latitude": -12.409
      }, 
      "id": 12510436
    }
  ]
}