{
  "type": "FeatureCollection", 
  "features": [
    {
      "geometry": {
        "type": "Polygon", 
        "coordinates": [
          [
            [
              6.859840, 
              46.954552
            ], 
            [
              6.859840, 
              46.961151
            ], 
            [
              6.869470, 
              46.961151
            ], 
            [
              6.869470, 
              46.954552
            ], 
            [
              6.859840, 
              46.954552
            ]
          ]
        ]
      }, 
      "type": "Feature", 
      "properties": {
        "lang": "ENG", 
        "name": "Aeroport de Neuchatel", 
        "hierarchy": [
          "woe:localadmin=12685268", 
          "woe:county=12593179", 
          "woe:state=2347094", 
          "woe:country=23424957", 
          "woe:planet=1"
        ], 
        "ne_latitude": 46.961151, 
        "sw_latitude": 46.954552, 
        "ne_longitude": 6.869470, 
        "longitude": 6.866040, 
        "iso": "CH", 
        "woe:placetype": "airport", 
        "provider": "geoplanet 7.6.0", 
        "latitude": 46.959991, 
        "sw_longitude": 6.859840, 
        "fullname": "Aeroport de Neuchatel, Areuse, Canton of Neuchatel, Switzerland", 
        "woe:id": 22656505, 
        "date_indexed": "2010-12-02T18:20:52Z", 
        "alias_FRE_Q": [
          "A\u00e9roport de Neuch\u00e2tel"
        ]
      }, 
      "id": 22656505
    }
  ]
}