{
  "type": "FeatureCollection", 
  "features": [
    {
      "geometry": {
        "type": "Polygon", 
        "coordinates": [
          [
            [
              19.033590, 
              50.235050
            ], 
            [
              19.033590, 
              50.244148
            ], 
            [
              19.047810, 
              50.244148
            ], 
            [
              19.047810, 
              50.235050
            ], 
            [
              19.033590, 
              50.235050
            ]
          ]
        ]
      }, 
      "type": "Feature", 
      "properties": {
        "lang": "ENG", 
        "name": "Katowice Airport", 
        "hierarchy": [
          "woe:localadmin=12618159", 
          "woe:county=12591397", 
          "woe:state=12577946", 
          "woe:country=23424923", 
          "woe:planet=1"
        ], 
        "ne_latitude": 50.244148, 
        "ne_longitude": 19.047810, 
        "longitude": 19.040701, 
        "iso": "PL", 
        "sw_latitude": 50.235050, 
        "provider": "geoplanet 7.6.0", 
        "latitude": 50.239601, 
        "sw_longitude": 19.033590, 
        "fullname": "Katowice Airport, Katowice, Silesian, Poland", 
        "woe:id": 12515319, 
        "date_indexed": "2010-12-02T12:12:45Z", 
        "woe:placetype": "airport"
      }, 
      "id": 12515319
    }
  ]
}