{
  "type": "FeatureCollection", 
  "features": [
    {
      "geometry": {
        "type": "Polygon", 
        "coordinates": [
          [
            [
              150.399, 
              -5.467
            ], 
            [
              150.399, 
              -5.458
            ], 
            [
              150.408, 
              -5.458
            ], 
            [
              150.408, 
              -5.467
            ], 
            [
              150.399, 
              -5.467
            ]
          ]
        ]
      }, 
      "type": "Feature", 
      "properties": {
        "lang": "ENG", 
        "alias_ENG_V": [
          "HKN"
        ], 
        "name": "Hoskins Airport", 
        "placetype": "airport", 
        "hierarchy": [
          "woe:state=2346597", 
          "woe:country=23424926", 
          "woe:planet=1"
        ], 
        "woeid": 12515468, 
        "ne_longitude": 150.408, 
        "longitude": 150.404, 
        "parent_woeid": 2346597, 
        "ne_latitude": -5.458, 
        "iso": "PG", 
        "sw_latitude": -5.467, 
        "provider": "geoplanet 7.6.0", 
        "latitude": -5.463, 
        "sw_longitude": 150.399, 
        "fullname": "Hoskins Airport, Hoskins, West New Britain, Papua New Guinea", 
        "iata_code": "HKN", 
        "date_indexed": "2010-12-02T09:57:28Z"
      }, 
      "id": 12515468
    }
  ]
}