{
  "type": "FeatureCollection", 
  "features": [
    {
      "geometry": {
        "type": "Polygon", 
        "coordinates": [
          [
            [
              -108.551521, 
              46.470242
            ], 
            [
              -108.551521, 
              46.478210
            ], 
            [
              -108.529541, 
              46.478210
            ], 
            [
              -108.529541, 
              46.470242
            ], 
            [
              -108.551521, 
              46.470242
            ]
          ]
        ]
      }, 
      "type": "Feature", 
      "properties": {
        "lang": "ENG", 
        "alias_ENG_V": [
          "RPX"
        ], 
        "name": "Roundup Airport", 
        "hierarchy": [
          "woe:county=12589113", 
          "woe:state=2347585", 
          "woe:country=23424977", 
          "woe:planet=1"
        ], 
        "ne_latitude": 46.478210, 
        "sw_latitude": 46.470242, 
        "ne_longitude": -108.529541, 
        "longitude": -108.549942, 
        "iso": "US", 
        "woe:placetype": "airport", 
        "provider": "geoplanet 7.6.0", 
        "latitude": 46.471691, 
        "sw_longitude": -108.551521, 
        "fullname": "Roundup Airport, Roundup, Montana, United States", 
        "woe:id": 12521664, 
        "date_indexed": "2010-12-02T18:39:45Z", 
        "iata:code": "RPX"
      }, 
      "id": 12521664
    }
  ]
}