{
  "type": "FeatureCollection", 
  "features": [
    {
      "geometry": {
        "type": "Polygon", 
        "coordinates": [
          [
            [
              21.408, 
              38.146
            ], 
            [
              21.408, 
              38.155
            ], 
            [
              21.419, 
              38.155
            ], 
            [
              21.419, 
              38.146
            ], 
            [
              21.408, 
              38.146
            ]
          ]
        ]
      }, 
      "type": "Feature", 
      "properties": {
        "lang": "ENG", 
        "woeid": 12513285, 
        "alias_UNK_V": [
          "Araxos"
        ], 
        "name": "Araxos Airport", 
        "alias_ENG_V": [
          "GPA"
        ], 
        "ne_latitude": 38.155, 
        "ne_longitude": 21.419, 
        "longitude": 21.414, 
        "parent_woeid": 957102, 
        "placetype": "Airport", 
        "iso": "GR", 
        "date_indexed": "2010-12-02T16:52:14Z", 
        "provider": "geoplanet 7.6.0", 
        "latitude": 38.150, 
        "sw_longitude": 21.408, 
        "fullname": "Araxos Airport, Metokhion, Dytiki Ellada, Achaia, Greece", 
        "sw_latitude": 38.146
      }, 
      "id": 12513285
    }
  ]
}