{
  "type": "FeatureCollection", 
  "features": [
    {
      "geometry": {
        "type": "Polygon", 
        "coordinates": [
          [
            [
              -6.239, 
              54.640
            ], 
            [
              -6.239, 
              54.666
            ], 
            [
              -6.190, 
              54.666
            ], 
            [
              -6.190, 
              54.640
            ], 
            [
              -6.239, 
              54.640
            ]
          ]
        ]
      }, 
      "type": "Feature", 
      "properties": {
        "alias_ENG_V": [
          "BFS"
        ], 
        "alias_SWE_Q": [
          "Belfast Internationella Flygplats"
        ], 
        "ne_latitude": 54.666, 
        "placetype": "Airport", 
        "alias_POR_Q": [
          "Aeroporto Internacional de Belfast"
        ], 
        "alias_ITA_Q": [
          "Aeroporto Internazionale Di Belfast"
        ], 
        "woeid": 12518031, 
        "alias_SPA_Q": [
          "Aeropuerto Internacional de Belfast"
        ], 
        "alias_FIN_Q": [
          "Belfastin International Lentokentt\u00e4"
        ], 
        "sw_longitude": -6.239, 
        "alias_FIN_V": [
          "Belfastin International Lentokentta"
        ], 
        "provider": "geoplanet 7.6.0", 
        "latitude": 54.662, 
        "alias_NOR_Q": [
          "Belfast Internasjonale Lufthavn"
        ], 
        "date_indexed": "2010-12-02T12:21:01Z", 
        "alias_DUT_Q": [
          "Internationale Luchthaven Belfast"
        ], 
        "alias_DAN_Q": [
          "Belfast Internationale Lufthavn"
        ], 
        "alias_GER_Q": [
          "International Flughafen Belfast"
        ], 
        "lang": "ENG", 
        "name": "Aldergrove Airport", 
        "parent_woeid": 44429, 
        "alias_UNK_Q": [
          "Medzinarodne Letisko Belfast"
        ], 
        "ne_longitude": -6.190, 
        "longitude": -6.217, 
        "iso": "GB", 
        "sw_latitude": 54.640, 
        "alias_FRE_V": [
          "Aeroport International de Belfast"
        ], 
        "fullname": "Aldergrove Airport, Aldergrove, Northern Ireland, Antrim, United Kingdom", 
        "alias_FRE_Q": [
          "A\u00e9roport International de Belfast"
        ]
      }, 
      "id": 12518031
    }
  ]
}