{
  "type": "FeatureCollection", 
  "features": [
    {
      "geometry": {
        "type": "Polygon", 
        "coordinates": [
          [
            [
              -110.239, 
              29.845
            ], 
            [
              -110.239, 
              29.855
            ], 
            [
              -110.228, 
              29.855
            ], 
            [
              -110.228, 
              29.845
            ], 
            [
              -110.239, 
              29.845
            ]
          ]
        ]
      }, 
      "type": "Feature", 
      "properties": {
        "lang": "ENG", 
        "woeid": 12523217, 
        "name": "San Felipe Airport", 
        "alias_ENG_V": [
          "SFH"
        ], 
        "ne_latitude": 29.855, 
        "provider": "geoplanet 7.6.0", 
        "ne_longitude": -110.228, 
        "longitude": -110.233, 
        "placetype": "Airport", 
        "iso": "MX", 
        "date_indexed": "2010-12-02T16:57:55Z", 
        "parent_woeid": 111065, 
        "latitude": 29.850, 
        "sw_longitude": -110.239, 
        "fullname": "San Felipe Airport, Aconchi, Sonora, Aconchi, Mexico", 
        "sw_latitude": 29.845
      }, 
      "id": 12523217
    }
  ]
}