{
  "type": "FeatureCollection", 
  "features": [
    {
      "geometry": {
        "type": "Polygon", 
        "coordinates": [
          [
            [
              -89.397, 
              35.200
            ], 
            [
              -89.397, 
              35.214
            ], 
            [
              -89.392, 
              35.214
            ], 
            [
              -89.392, 
              35.200
            ], 
            [
              -89.397, 
              35.200
            ]
          ]
        ]
      }, 
      "type": "Feature", 
      "properties": {
        "lang": "ENG", 
        "alias_ENG_V": [
          "FYE"
        ], 
        "name": "Fayette County Airport", 
        "placetype": "airport", 
        "hierarchy": [
          "woe:county=12589935", 
          "woe:state=2347601", 
          "woe:country=23424977", 
          "woe:planet=1"
        ], 
        "woeid": 12519715, 
        "ne_longitude": -89.392, 
        "longitude": -89.393, 
        "parent_woeid": 12589935, 
        "ne_latitude": 35.214, 
        "iso": "US", 
        "sw_latitude": 35.200, 
        "provider": "geoplanet 7.6.0", 
        "latitude": 35.207, 
        "sw_longitude": -89.397, 
        "fullname": "Fayette County Airport, Somerville, Tennessee, United States", 
        "date_indexed": "2010-12-02T18:39:38Z"
      }, 
      "id": 12519715
    }
  ]
}