{
  "type": "FeatureCollection", 
  "features": [
    {
      "geometry": {
        "type": "Polygon", 
        "coordinates": [
          [
            [
              156.708, 
              53.012
            ], 
            [
              156.708, 
              53.022
            ], 
            [
              156.723, 
              53.022
            ], 
            [
              156.723, 
              53.012
            ], 
            [
              156.708, 
              53.012
            ]
          ]
        ]
      }, 
      "type": "Feature", 
      "properties": {
        "lang": "ENG", 
        "ne_latitude": 53.022, 
        "name": "Karymay Airport", 
        "hierarchy": [
          "woe:county=12598427", 
          "woe:state=20070514", 
          "woe:country=23424936", 
          "woe:planet=1"
        ], 
        "provider": "geoplanet 7.6.0", 
        "ne_longitude": 156.723, 
        "longitude": 156.716, 
        "iso": "RU", 
        "date_indexed": "2010-12-02T16:10:58Z", 
        "latitude": 53.017, 
        "sw_longitude": 156.708, 
        "fullname": "Karymay Airport, Kamchatskaya Oblast, Ust-Bolsheretsky, Russia", 
        "woe:id": 12516102, 
        "sw_latitude": 53.012, 
        "woe:placetype": "airport"
      }, 
      "id": 12516102
    }
  ]
}