{
  "type": "FeatureCollection", 
  "features": [
    {
      "geometry": {
        "type": "Polygon", 
        "coordinates": [
          [
            [
              12.286, 
              47.923
            ], 
            [
              12.286, 
              47.928
            ], 
            [
              12.290, 
              47.928
            ], 
            [
              12.290, 
              47.923
            ], 
            [
              12.286, 
              47.923
            ]
          ]
        ]
      }, 
      "type": "Feature", 
      "properties": {
        "lang": "GER", 
        "ne_latitude": 47.928, 
        "name": "Flugplatz Bad Endorf", 
        "hierarchy": [
          "woe:localadmin=12622769", 
          "woe:county=12596730", 
          "woe:state=2345482", 
          "woe:country=23424829", 
          "woe:planet=1"
        ], 
        "provider": "geoplanet 7.6.0", 
        "ne_longitude": 12.290, 
        "longitude": 12.289, 
        "iso": "DE", 
        "date_indexed": "2010-12-02T09:50:31Z", 
        "latitude": 47.923, 
        "sw_longitude": 12.286, 
        "fullname": "Flugplatz Bad Endorf, Bad Endorf, Bavaria, Germany", 
        "woe:id": 56051965, 
        "sw_latitude": 47.923, 
        "woe:placetype": "airport"
      }, 
      "id": 56051965
    }
  ]
}