{
  "type": "FeatureCollection", 
  "features": [
    {
      "geometry": {
        "type": "Polygon", 
        "coordinates": [
          [
            [
              74.501, 
              46.612
            ], 
            [
              74.501, 
              46.621
            ], 
            [
              74.515, 
              46.621
            ], 
            [
              74.515, 
              46.612
            ], 
            [
              74.501, 
              46.612
            ]
          ]
        ]
      }, 
      "type": "Feature", 
      "properties": {
        "lang": "ENG", 
        "woeid": 12514484, 
        "name": "Targyz Airport", 
        "ne_latitude": 46.621, 
        "provider": "geoplanet 7.6.0", 
        "ne_longitude": 74.515, 
        "longitude": 74.508, 
        "placetype": "Airport", 
        "iso": "KZ", 
        "date_indexed": "2010-12-02T08:54:13Z", 
        "parent_woeid": 2257573, 
        "latitude": 46.616, 
        "sw_longitude": 74.501, 
        "fullname": "Targyz Airport, Qaraghandy, Kazakhstan", 
        "sw_latitude": 46.612
      }, 
      "id": 12514484
    }
  ]
}