{
  "type": "FeatureCollection", 
  "features": [
    {
      "geometry": {
        "type": "Polygon", 
        "coordinates": [
          [
            [
              33.714, 
              57.549
            ], 
            [
              33.714, 
              57.558
            ], 
            [
              33.731, 
              57.558
            ], 
            [
              33.731, 
              57.549
            ], 
            [
              33.714, 
              57.549
            ]
          ]
        ]
      }, 
      "type": "Feature", 
      "properties": {
        "lang": "ENG", 
        "woeid": 12515979, 
        "name": "Firovo Airport", 
        "ne_latitude": 57.558, 
        "provider": "geoplanet 7.6.0", 
        "ne_longitude": 33.731, 
        "longitude": 33.723, 
        "placetype": "Airport", 
        "iso": "RU", 
        "date_indexed": "2010-12-02T16:10:58Z", 
        "parent_woeid": 2120797, 
        "latitude": 57.554, 
        "sw_longitude": 33.714, 
        "fullname": "Firovo Airport, Firovo, Tverskaya Oblast, Firovsky, Russia", 
        "sw_latitude": 57.549
      }, 
      "id": 12515979
    }
  ]
}